{
    "command":{
        "CMD": [
        
            "assoc",
            "break",
            "call",
            "cd",
            "chdir",
            "cls",
            "color",
            "command",
            "copy",
            "date",
            "del",
            "erase",
            "dir",
            "echo",
            "endlocal",
            "exit",
            "for",
            "ftype",
            "goto",
            "if",
            "md",
            "mkdir",
            "move",
            "path",
            "pause",
            "popd",
            "pushd",
            "rd",
            "rmdir",
            "rem",
            "ren",
            "rename",
            "set",
            "setlocal",
            "shift",
            "start",
            "time",
            "title",
            "type",
            "ver",
            "verify",
            "vol",
            "help",
            "attrib",
            "bcdedit",
            "bootcfg",
            "cacls",
            "certutil",
            "chcp",
            "chkdsk",
            "cipher",
            "choice",
            "compact",
            "convert",
            "defrag",
            "dism",
            "diskpart",
            "diskshadow",
            "diskperf",
            "driverquery",
            "fc",
            "find",
            "findstr",
            "format",
            "fsutil",
            "getmac",
            "gpresult",
            "gpupdate",
            "hostname",
            "icacls",
            "inetmgr",
            "ipconfig",
            "ipsec",
            "klist",
            "ksetup",
            "label",
            "lodctr",
            "logman",
            "manage-bde",
            "mdsched",
            "mklink",
            "mode",
            "mountvol",
            "mshta",
            "msinfo32",
            "msiexec",
            "nbtstat",
            "net",
            "netcfg",
            "netdom",
            "netsh",
            "netstat",
            "nslookup",
            "nltest",
            "nls_util",
            "openfiles",
            "pathping",
            "perfmon",
            "pnputil",
            "powercfg",
            "powershell",
            "printbrm",
            "printui",
            "prnmngr",
            "prompt",
            "rasdial",
            "reg",
            "regedt32",
            "regini",
            "regsvr32",
            "relog",
            "replace",
            "robocopy",
            "route",
            "rwinsta",
            "schtasks",
            "sc",
            "sdbinst",
            "secedit",
            "setx",
            "shutdown",
            "sigverif",
            "slmgr",
            "sfc",
            "systeminfo",
            "takeown",
            "telnet",
            "tftp",
            "timeout",
            "tlist",
            "tracert",
            "tracerpt",
            "typeperf",
            "unlodctr",
            "verifier",
            "vssadmin",
            "wevtutil",
            "whoami",
            "winrm",
            "winsat",
            "winver",
            "wmic",
            "w32tm",
            "wusa",
            "xcopy",
            "finger",
            "ftp",
            "ftp32",
            "net use",
            "net view",
            "tasklist",
            "taskkill",
            "taskeng",
            "taskschd.msc",
            "tscon",
            "tsdiscon",
            "tskill",
            "resmon",
            "eventcreate",
            "eventquery",
            "eventtriggers",
            "rundll32",
            "more",
            "clip",
            "expand",
            "certreq",
            "edlin",
            "debug",
            "edit",
            "at",
            "net send",
            "rsh",
            "rexec"

        ]
        ,"custom" :[
            "download"
        ]
        , "scriptforfolder" : {
            "download": "path/to/download_fuctnality.cs"
        }
    }
    ,"flags" :{
        "flaglist" : [
            "-x"
        ]
        ,"flaglistthatshouldbeencluededinthefinaljson" : [
            "-x"
        ]
    }
}